{
  "info": {
    "name": "Smart Notes Workspace",
    "description": "API collection for Smart Notes Workspace project",
    "schema": "https://schema.getpostman.com/json/collection/v2.1.0/collection.json"
  },
  "item": [
    {
      "name": "Auth",
      "item": [
        {
          "name": "Register",
          "request": {
            "method": "POST",
            "header": [
              {
                "key": "Content-Type",
                "value": "application/json"
              }
            ],
            "body": {
              "mode": "raw",
              "raw": "{\n    \"name\": \"Test User\",\n    \"email\": \"test@example.com\",\n    \"password\": \"password123\"\n}"
            },
            "url": {
              "raw": "http://localhost:5000/api/auth/register",
              "protocol": "http",
              "host": ["localhost"],
              "port": "5000",
              "path": ["api", "auth", "register"]
            }
          }
        },
        {
          "name": "Login",
          "request": {
            "method": "POST",
            "header": [
              {
                "key": "Content-Type",
                "value": "application/json"
              }
            ],
            "body": {
              "mode": "raw",
              "raw": "{\n    \"email\": \"test@example.com\",\n    \"password\": \"password123\"\n}"
            },
            "url": {
              "raw": "http://localhost:5000/api/auth/login",
              "protocol": "http",
              "host": ["localhost"],
              "port": "5000",
              "path": ["api", "auth", "login"]
            }
          }
        }
      ]
    },
    {
      "name": "Notes",
      "item": [
        {
          "name": "Get Notes",
          "request": {
            "method": "GET",
            "header": [
              {
                "key": "Authorization",
                "value": "Bearer {{token}}"
              }
            ],
            "url": {
              "raw": "http://localhost:5000/api/notes",
              "protocol": "http",
              "host": ["localhost"],
              "port": "5000",
              "path": ["api", "notes"]
            }
          }
        },
        {
          "name": "Create Note",
          "request": {
            "method": "POST",
            "header": [
              {
                "key": "Authorization",
                "value": "Bearer {{token}}"
              },
              {
                "key": "Content-Type",
                "value": "application/json"
              }
            ],
            "body": {
              "mode": "raw",
              "raw": "{\n    \"title\": \"My First Note\",\n    \"content\": \"# Hello World\\nThis is a markdown note.\",\n    \"category\": \"General\",\n    \"status\": \"Draft\"\n}"
            },
            "url": {
              "raw": "http://localhost:5000/api/notes",
              "protocol": "http",
              "host": ["localhost"],
              "port": "5000",
              "path": ["api", "notes"]
            }
          }
        }
      ]
    }
  ]
}
